wurlitzer.py
wurlitzer-3.1.0.dist-info/LICENSE
wurlitzer-3.1.0.dist-info/METADATA
wurlitzer-3.1.0.dist-info/WHEEL
wurlitzer-3.1.0.dist-info/top_level.txt
wurlitzer-3.1.0.dist-info/RECORD
