Metadata-Version: 2.1
Name: wurlitzer
Version: 3.1.0
Summary: Capture C-level output in context managers
Home-page: https://github.com/minrk/wurlitzer
Author: Min RK
Author-email: benjaminrk@gmail.com
License: MIT
Classifier: Development Status :: 4 - Beta
Classifier: Intended Audience :: Developers
Classifier: License :: OSI Approved :: MIT License
Classifier: Programming Language :: Python :: 3
Requires-Python: >=3.5
License-File: LICENSE
